lightman_ai/__init__.py
lightman_ai/cli.py
lightman_ai/constants.py
lightman_ai/exceptions.py
lightman_ai/main.py
lightman_ai/py.typed
lightman_ai/utils.py
lightman_ai/ai/utils.py
lightman_ai/ai/base/__init__.py
lightman_ai/ai/base/agent.py
lightman_ai/ai/base/exceptions.py
lightman_ai/ai/gemini/__init__.py
lightman_ai/ai/gemini/agent.py
lightman_ai/ai/gemini/exceptions.py
lightman_ai/ai/openai/__init__.py
lightman_ai/ai/openai/agent.py
lightman_ai/ai/openai/exceptions.py
lightman_ai/article/__init__.py
lightman_ai/article/exceptions.py
lightman_ai/article/models.py
lightman_ai/core/__init__.py
lightman_ai/core/config.py
lightman_ai/core/exceptions.py
lightman_ai/core/sentry.py
lightman_ai/integrations/__init__.py
lightman_ai/integrations/service_desk/__init__.py
lightman_ai/integrations/service_desk/constants.py
lightman_ai/integrations/service_desk/exceptions.py
lightman_ai/integrations/service_desk/integration.py
lightman_ai/sources/base.py
lightman_ai/sources/exceptions.py
lightman_ai/sources/the_hacker_news.py
lightman_ai-1.2.3.dist-info/METADATA
lightman_ai-1.2.3.dist-info/WHEEL
lightman_ai-1.2.3.dist-info/entry_points.txt
lightman_ai-1.2.3.dist-info/licenses/LICENSE
lightman_ai-1.2.3.dist-info/RECORD
