Metadata-Version: 2.4
Name: lightman_ai
Version: 1.2.3
Summary: LLM-powered cybersecurity news aggregator.
Author-email: sdn4z <imsdn4z@gmail.com>, scastlara <s.cast.lara@gmail.com>
License-File: LICENSE
Requires-Python: <4,>=3.13
Requires-Dist: click<9.0.0,>=8.1.7
Requires-Dist: httpx<1.0.0,>=0.28.0
Requires-Dist: pydantic-ai-slim[google,openai]<2.0.0,>=1.0.0
Requires-Dist: pydantic-settings<3.0.0,>=2.9.1
Requires-Dist: python-dotenv<2.0.0,>=1.1.1
Requires-Dist: stamina<26.0.0,>=25.1.0
Requires-Dist: tomlkit<1.0.0,>=0.13.3
Provides-Extra: sentry
Requires-Dist: sentry-sdk<3.0.0,>=2.21.0; extra == 'sentry'
